turing_data_transformation_library/__init__.py
turing_data_transformation_library/cross_correlation.py
turing_data_transformation_library/time_series_windowing.py
turing_data_transformation_library/transpose.py
turing_data_transformation_library/utils.py
turing_data_transformation_library-0.1.3.dist-info/METADATA
turing_data_transformation_library-0.1.3.dist-info/WHEEL
turing_data_transformation_library-0.1.3.dist-info/RECORD
