Metadata-Version: 2.1
Name: turing_data_transformation_library
Version: 0.1.3
Summary: 
Author: Vytautas Pliadis
Author-email: vytautas.pliadis@gmail.com
Requires-Python: >=3.11.0,<4.0.0
Classifier: Programming Language :: Python :: 3
Classifier: Programming Language :: Python :: 3.11
Classifier: Programming Language :: Python :: 3.12
Requires-Dist: numpy (>=1.26.3,<2.0.0)
Requires-Dist: pytest (>=7.4.3,<8.0.0)
